<annotation>
	<folder>ToLabel</folder>
	<filename>R02_A04_18_x40392_y22032.tif</filename>
	<path>E:\Label\ToLabel\R02_A04_18_x40392_y22032.tif</path>
	<source>
		<database>Unknown</database>
	</source>
	<size>
		<width>2040</width>
		<height>2040</height>
		<depth>3</depth>
	</size>
	<segmented>0</segmented>
	<object>
		<name>red</name>
		<pose>Unspecified</pose>
		<truncated>0</truncated>
		<difficult>0</difficult>
		<bndbox>
			<xmin>1827</xmin>
			<ymin>197</ymin>
			<xmax>1884</xmax>
			<ymax>255</ymax>
		</bndbox>
	</object>
	<object>
		<name>red</name>
		<pose>Unspecified</pose>
		<truncated>0</truncated>
		<difficult>0</difficult>
		<bndbox>
			<xmin>1765</xmin>
			<ymin>1211</ymin>
			<xmax>1838</xmax>
			<ymax>1305</ymax>
		</bndbox>
	</object>
	<object>
		<name>red</name>
		<pose>Unspecified</pose>
		<truncated>0</truncated>
		<difficult>0</difficult>
		<bndbox>
			<xmin>1840</xmin>
			<ymin>1395</ymin>
			<xmax>1921</xmax>
			<ymax>1486</ymax>
		</bndbox>
	</object>
	<object>
		<name>red</name>
		<pose>Unspecified</pose>
		<truncated>0</truncated>
		<difficult>0</difficult>
		<bndbox>
			<xmin>575</xmin>
			<ymin>880</ymin>
			<xmax>650</xmax>
			<ymax>943</ymax>
		</bndbox>
	</object>
	<object>
		<name>red</name>
		<pose>Unspecified</pose>
		<truncated>0</truncated>
		<difficult>0</difficult>
		<bndbox>
			<xmin>1184</xmin>
			<ymin>1236</ymin>
			<xmax>1275</xmax>
			<ymax>1315</ymax>
		</bndbox>
	</object>
</annotation>
