<annotation>
	<folder>IMG</folder>
	<filename>0167_R02_A07_01_x25704_y53244.png</filename>
	<path>I:\Dzw\SCZ_data\IMG\0167_R02_A07_01_x25704_y53244.png</path>
	<source>
		<database>Unknown</database>
	</source>
	<size>
		<width>2040</width>
		<height>2040</height>
		<depth>3</depth>
	</size>
	<segmented>0</segmented>
	<object>
		<name>red</name>
		<pose>Unspecified</pose>
		<truncated>0</truncated>
		<difficult>0</difficult>
		<bndbox>
			<xmin>577</xmin>
			<ymin>670</ymin>
			<xmax>661</xmax>
			<ymax>743</ymax>
		</bndbox>
	</object>
	<object>
		<name>red</name>
		<pose>Unspecified</pose>
		<truncated>0</truncated>
		<difficult>0</difficult>
		<bndbox>
			<xmin>402</xmin>
			<ymin>1115</ymin>
			<xmax>465</xmax>
			<ymax>1193</ymax>
		</bndbox>
	</object>
	<object>
		<name>red</name>
		<pose>Unspecified</pose>
		<truncated>0</truncated>
		<difficult>0</difficult>
		<bndbox>
			<xmin>1175</xmin>
			<ymin>1024</ymin>
			<xmax>1250</xmax>
			<ymax>1105</ymax>
		</bndbox>
	</object>
	<object>
		<name>red</name>
		<pose>Unspecified</pose>
		<truncated>0</truncated>
		<difficult>0</difficult>
		<bndbox>
			<xmin>1600</xmin>
			<ymin>1180</ymin>
			<xmax>1650</xmax>
			<ymax>1257</ymax>
		</bndbox>
	</object>
	<object>
		<name>red</name>
		<pose>Unspecified</pose>
		<truncated>0</truncated>
		<difficult>0</difficult>
		<bndbox>
			<xmin>856</xmin>
			<ymin>1349</ymin>
			<xmax>917</xmax>
			<ymax>1413</ymax>
		</bndbox>
	</object>
	<object>
		<name>red</name>
		<pose>Unspecified</pose>
		<truncated>0</truncated>
		<difficult>0</difficult>
		<bndbox>
			<xmin>421</xmin>
			<ymin>1409</ymin>
			<xmax>489</xmax>
			<ymax>1478</ymax>
		</bndbox>
	</object>
	<object>
		<name>red</name>
		<pose>Unspecified</pose>
		<truncated>0</truncated>
		<difficult>0</difficult>
		<bndbox>
			<xmin>1029</xmin>
			<ymin>951</ymin>
			<xmax>1102</xmax>
			<ymax>1007</ymax>
		</bndbox>
	</object>
</annotation>
