<annotation>
	<folder>IMG</folder>
	<filename>0205_R02_A10_03_x115668_y51408.png</filename>
	<path>I:\Dzw\SCZ_data\IMG\0205_R02_A10_03_x115668_y51408.png</path>
	<source>
		<database>Unknown</database>
	</source>
	<size>
		<width>2040</width>
		<height>2040</height>
		<depth>3</depth>
	</size>
	<segmented>0</segmented>
	<object>
		<name>green</name>
		<pose>Unspecified</pose>
		<truncated>0</truncated>
		<difficult>0</difficult>
		<bndbox>
			<xmin>330</xmin>
			<ymin>879</ymin>
			<xmax>420</xmax>
			<ymax>969</ymax>
		</bndbox>
	</object>
	<object>
		<name>green</name>
		<pose>Unspecified</pose>
		<truncated>0</truncated>
		<difficult>0</difficult>
		<bndbox>
			<xmin>130</xmin>
			<ymin>927</ymin>
			<xmax>220</xmax>
			<ymax>1017</ymax>
		</bndbox>
	</object>
	<object>
		<name>green</name>
		<pose>Unspecified</pose>
		<truncated>0</truncated>
		<difficult>0</difficult>
		<bndbox>
			<xmin>712</xmin>
			<ymin>935</ymin>
			<xmax>802</xmax>
			<ymax>1025</ymax>
		</bndbox>
	</object>
	<object>
		<name>green</name>
		<pose>Unspecified</pose>
		<truncated>0</truncated>
		<difficult>0</difficult>
		<bndbox>
			<xmin>106</xmin>
			<ymin>1087</ymin>
			<xmax>196</xmax>
			<ymax>1177</ymax>
		</bndbox>
	</object>
	<object>
		<name>green</name>
		<pose>Unspecified</pose>
		<truncated>0</truncated>
		<difficult>0</difficult>
		<bndbox>
			<xmin>377</xmin>
			<ymin>1437</ymin>
			<xmax>467</xmax>
			<ymax>1527</ymax>
		</bndbox>
	</object>
	<object>
		<name>green</name>
		<pose>Unspecified</pose>
		<truncated>0</truncated>
		<difficult>0</difficult>
		<bndbox>
			<xmin>1429</xmin>
			<ymin>1493</ymin>
			<xmax>1519</xmax>
			<ymax>1583</ymax>
		</bndbox>
	</object>
	<object>
		<name>green</name>
		<pose>Unspecified</pose>
		<truncated>0</truncated>
		<difficult>0</difficult>
		<bndbox>
			<xmin>696</xmin>
			<ymin>1501</ymin>
			<xmax>786</xmax>
			<ymax>1591</ymax>
		</bndbox>
	</object>
	<object>
		<name>green</name>
		<pose>Unspecified</pose>
		<truncated>0</truncated>
		<difficult>0</difficult>
		<bndbox>
			<xmin>417</xmin>
			<ymin>1509</ymin>
			<xmax>507</xmax>
			<ymax>1599</ymax>
		</bndbox>
	</object>
	<object>
		<name>green</name>
		<pose>Unspecified</pose>
		<truncated>1</truncated>
		<difficult>0</difficult>
		<bndbox>
			<xmin>1</xmin>
			<ymin>1541</ymin>
			<xmax>85</xmax>
			<ymax>1631</ymax>
		</bndbox>
	</object>
	<object>
		<name>green</name>
		<pose>Unspecified</pose>
		<truncated>0</truncated>
		<difficult>0</difficult>
		<bndbox>
			<xmin>1676</xmin>
			<ymin>1708</ymin>
			<xmax>1766</xmax>
			<ymax>1798</ymax>
		</bndbox>
	</object>
	<object>
		<name>green</name>
		<pose>Unspecified</pose>
		<truncated>0</truncated>
		<difficult>0</difficult>
		<bndbox>
			<xmin>1931</xmin>
			<ymin>1756</ymin>
			<xmax>2021</xmax>
			<ymax>1846</ymax>
		</bndbox>
	</object>
	<object>
		<name>green</name>
		<pose>Unspecified</pose>
		<truncated>0</truncated>
		<difficult>0</difficult>
		<bndbox>
			<xmin>1277</xmin>
			<ymin>1397</ymin>
			<xmax>1344</xmax>
			<ymax>1461</ymax>
		</bndbox>
	</object>
	<object>
		<name>green</name>
		<pose>Unspecified</pose>
		<truncated>0</truncated>
		<difficult>0</difficult>
		<bndbox>
			<xmin>120</xmin>
			<ymin>1155</ymin>
			<xmax>203</xmax>
			<ymax>1237</ymax>
		</bndbox>
	</object>
</annotation>
