<annotation>
	<folder>IMG</folder>
	<filename>R02_A22_06_x23868_y75276.tif</filename>
	<path>I:\Dzw\SCZ_data\IMG\R02_A22_06_x23868_y75276.tif</path>
	<source>
		<database>Unknown</database>
	</source>
	<size>
		<width>2040</width>
		<height>2040</height>
		<depth>3</depth>
	</size>
	<segmented>0</segmented>
	<object>
		<name>green</name>
		<pose>Unspecified</pose>
		<truncated>0</truncated>
		<difficult>0</difficult>
		<bndbox>
			<xmin>261</xmin>
			<ymin>13</ymin>
			<xmax>327</xmax>
			<ymax>90</ymax>
		</bndbox>
	</object>
	<object>
		<name>green</name>
		<pose>Unspecified</pose>
		<truncated>0</truncated>
		<difficult>0</difficult>
		<bndbox>
			<xmin>367</xmin>
			<ymin>393</ymin>
			<xmax>429</xmax>
			<ymax>463</ymax>
		</bndbox>
	</object>
	<object>
		<name>green</name>
		<pose>Unspecified</pose>
		<truncated>0</truncated>
		<difficult>0</difficult>
		<bndbox>
			<xmin>275</xmin>
			<ymin>786</ymin>
			<xmax>327</xmax>
			<ymax>849</ymax>
		</bndbox>
	</object>
	<object>
		<name>green</name>
		<pose>Unspecified</pose>
		<truncated>0</truncated>
		<difficult>0</difficult>
		<bndbox>
			<xmin>1127</xmin>
			<ymin>659</ymin>
			<xmax>1188</xmax>
			<ymax>722</ymax>
		</bndbox>
	</object>
	<object>
		<name>green</name>
		<pose>Unspecified</pose>
		<truncated>0</truncated>
		<difficult>0</difficult>
		<bndbox>
			<xmin>642</xmin>
			<ymin>822</ymin>
			<xmax>727</xmax>
			<ymax>903</ymax>
		</bndbox>
	</object>
	<object>
		<name>green</name>
		<pose>Unspecified</pose>
		<truncated>0</truncated>
		<difficult>0</difficult>
		<bndbox>
			<xmin>667</xmin>
			<ymin>286</ymin>
			<xmax>767</xmax>
			<ymax>382</ymax>
		</bndbox>
	</object>
	<object>
		<name>green</name>
		<pose>Unspecified</pose>
		<truncated>0</truncated>
		<difficult>0</difficult>
		<bndbox>
			<xmin>1300</xmin>
			<ymin>974</ymin>
			<xmax>1371</xmax>
			<ymax>1038</ymax>
		</bndbox>
	</object>
	<object>
		<name>green</name>
		<pose>Unspecified</pose>
		<truncated>0</truncated>
		<difficult>0</difficult>
		<bndbox>
			<xmin>771</xmin>
			<ymin>103</ymin>
			<xmax>862</xmax>
			<ymax>147</ymax>
		</bndbox>
	</object>
	<object>
		<name>green</name>
		<pose>Unspecified</pose>
		<truncated>0</truncated>
		<difficult>0</difficult>
		<bndbox>
			<xmin>983</xmin>
			<ymin>1022</ymin>
			<xmax>1037</xmax>
			<ymax>1090</ymax>
		</bndbox>
	</object>
	<object>
		<name>green</name>
		<pose>Unspecified</pose>
		<truncated>0</truncated>
		<difficult>0</difficult>
		<bndbox>
			<xmin>960</xmin>
			<ymin>107</ymin>
			<xmax>1021</xmax>
			<ymax>174</ymax>
		</bndbox>
	</object>
</annotation>
