<annotation>
	<folder>last+</folder>
	<filename>R02_A35_02_x148716_y82620.png</filename>
	<path>C:\Users\dzw_unicorn\Desktop\last+\last+\R02_A35_02_x148716_y82620.png</path>
	<source>
		<database>Unknown</database>
	</source>
	<size>
		<width>2040</width>
		<height>2040</height>
		<depth>3</depth>
	</size>
	<segmented>0</segmented>
	<object>
		<name>green</name>
		<pose>Unspecified</pose>
		<truncated>0</truncated>
		<difficult>0</difficult>
		<bndbox>
			<xmin>1238</xmin>
			<ymin>27</ymin>
			<xmax>1328</xmax>
			<ymax>117</ymax>
		</bndbox>
	</object>
<object>
		<name>green</name>
		<pose>Unspecified</pose>
		<truncated>0</truncated>
		<difficult>0</difficult>
		<bndbox>
			<xmin>736</xmin>
			<ymin>98</ymin>
			<xmax>826</xmax>
			<ymax>188</ymax>
		</bndbox>
	</object>
<object>
		<name>green</name>
		<pose>Unspecified</pose>
		<truncated>0</truncated>
		<difficult>0</difficult>
		<bndbox>
			<xmin>1533</xmin>
			<ymin>178</ymin>
			<xmax>1623</xmax>
			<ymax>268</ymax>
		</bndbox>
	</object>
<object>
		<name>green</name>
		<pose>Unspecified</pose>
		<truncated>0</truncated>
		<difficult>0</difficult>
		<bndbox>
			<xmin>377</xmin>
			<ymin>616</ymin>
			<xmax>467</xmax>
			<ymax>706</ymax>
		</bndbox>
	</object>
<object>
		<name>green</name>
		<pose>Unspecified</pose>
		<truncated>0</truncated>
		<difficult>0</difficult>
		<bndbox>
			<xmin>1589</xmin>
			<ymin>672</ymin>
			<xmax>1679</xmax>
			<ymax>762</ymax>
		</bndbox>
	</object>
<object>
		<name>green</name>
		<pose>Unspecified</pose>
		<truncated>0</truncated>
		<difficult>0</difficult>
		<bndbox>
			<xmin>1636</xmin>
			<ymin>776</ymin>
			<xmax>1726</xmax>
			<ymax>866</ymax>
		</bndbox>
	</object>
<object>
		<name>red</name>
		<pose>Unspecified</pose>
		<truncated>0</truncated>
		<difficult>0</difficult>
		<bndbox>
			<xmin>1342</xmin>
			<ymin>824</ymin>
			<xmax>1432</xmax>
			<ymax>914</ymax>
		</bndbox>
	</object>
</annotation>